{"response": [{"VoltageMax": 14.3, "HumidityMean": 80, "ConcentrationMin": 2, "HumidityMin": 56, "ConcentrationMean": 4, "date": "02/18/12", "stationChartLink": "https://wrcc.dri.edu/cgi-bin/rawMAIN4.pl?idsm13+18+02+12+M", "TempMin": 7.2, "TempMax": 17.6, "BaroPress": 992, "name": "Smoke #13", "ConcentrationMax": 6, "LastObv": "24:00", "VoltageMean": 14.2, "WindAvg": 0.5, "qcReportLink": "https://tools.airfire.org/monitor-qc-report/v4/wrcc?unitID=sm13", "AirFlowMean": 2, "HumidityMax": 95, "WindDir": 143, "TempMean": 11.5, "stationId": "sm13", "longitude": -85.9439, "VoltageMin": 14.1, "latitude": 33.5154}, {"qcReportLink": "https://tools.airfire.org/monitor-qc-report/v2/wrcc?unitID=sm67", "LastObv": "17:00", "HumidityMean": 44, "ConcentrationMean": 43565, "name": "Smoke RMK 107 (Smoke #67)", "ConcentrationMax": 43565, "latitude": 43.565, "WindDir": "", "VoltageMean": 43.8, "TempMin": 0, "AirFlowMean": 48.94, "BaroPress": -1.2, "longitude": -116.2087, "stationChartLink": "https://wrcc.dri.edu/cgi-bin/rawMAIN4.pl?idsm67+18+02+12+M", "VoltageMax": 49, "VoltageMin": 2, "WindAvg": 41, "HumidityMax": "", "HumidityMin": "", "TempMax": 23, "date": "02/18/12", "stationId": "sm67", "ConcentrationMin": 43565, "TempMean": 8.4}, {"latitude": 33.1996, "TempMin": 9.1, "qcReportLink": "https://tools.airfire.org/monitor-qc-report/v2/wrcc?unitID=sm24", "WindAvg": 2.1, "VoltageMean": 14.1, "WindDir": "", "HumidityMin": 59, "name": "Smoke RMK 119 (Smoke #24)", "LastObv": "22:00", "TempMax": 17.3, "longitude": -86.1925, "VoltageMax": 14.4, "TempMean": 12.2, "date": "02/18/12", "BaroPress": 951.6, "AirFlowMean": 2, "ConcentrationMin": 3, "HumidityMean": 84, "ConcentrationMean": 4, "HumidityMax": 92, "ConcentrationMax": 6, "stationChartLink": "https://wrcc.dri.edu/cgi-bin/rawMAIN4.pl?idsm24+18+02+12+M", "VoltageMin": 9, "stationId": "sm24"}]}