{"response": [{"AirFlowMean": 2, "latitude": 44.4363, "HumidityMean": 45, "name": "Smoke #13", "TempMax": 33.4, "qcReportLink": "https://tools.airfire.org/monitor-qc-report/v4/wrcc?unitID=sm13", "ConcentrationMin": 0, "BaroPress": 877.8, "VoltageMean": 14.1, "stationChartLink": "https://wrcc.dri.edu/cgi-bin/rawMAIN4.pl?idsm13+05+09+14+M", "HumidityMin": 9, "WindAvg": 0.8, "HumidityMax": 81, "TempMean": 15.2, "WindDir": 81, "date": "09/05/14", "longitude": -118.1893, "ConcentrationMean": 0, "VoltageMax": 14.4, "stationId": "sm13", "TempMin": 1.1, "LastObv": "24:00", "VoltageMin": 13.8, "ConcentrationMax": 0}, {"qcReportLink": "https://tools.airfire.org/monitor-qc-report/v2/wrcc?unitID=s215", "stationChartLink": "https://wrcc.dri.edu/cgi-bin/rawMAIN4.pl?ids215+05+09+14+M", "date": "09/05/14", "HumidityMax": 75, "WindDir": 285, "latitude": 44.2609, "TempMean": 17.8, "WindAvg": 1.7, "TempMin": 6.4, "VoltageMean": 14.2, "stationId": "s215", "name": "Smoke RMK 110 (Smoke #215)", "AirFlowMean": 2, "ConcentrationMax": 2, "ConcentrationMin": 0, "VoltageMin": 14, "HumidityMean": 47, "BaroPress": 912, "VoltageMax": 14.4, "LastObv": "24:00", "longitude": -121.1469, "HumidityMin": 23, "TempMax": 29.6, "ConcentrationMean": 0}, {"LastObv": "24:00", "HumidityMin": 11, "latitude": 43.9145, "ConcentrationMean": 2, "TempMean": 21.6, "HumidityMax": 86, "WindDir": 116, "TempMax": 38.9, "VoltageMax": 14.4, "qcReportLink": "https://tools.airfire.org/monitor-qc-report/v2/wrcc?unitID=sm19", "AirFlowMean": 2, "TempMin": 8.4, "stationId": "sm19", "ConcentrationMax": 12, "date": "09/05/14", "name": "Smoke RMK 114 (Smoke #19)", "WindAvg": 1.4, "stationChartLink": "https://wrcc.dri.edu/cgi-bin/rawMAIN4.pl?idsm19+05+09+14+M", "VoltageMin": 13.9, "longitude": -122.8224, "VoltageMean": 14.2, "ConcentrationMin": 0, "HumidityMean": 51, "BaroPress": ""}, {"qcReportLink": "https://tools.airfire.org/monitor-qc-report/v2/wrcc?unitID=sm20", "longitude": -122.5343, "latitude": 43.7593, "AirFlowMean": 2, "TempMax": 37.2, "LastObv": "24:00", "HumidityMean": 58, "ConcentrationMean": 29, "VoltageMin": 14, "TempMean": 20.1, "WindDir": 168, "stationChartLink": "https://wrcc.dri.edu/cgi-bin/rawMAIN4.pl?idsm20+05+09+14+M", "TempMin": 10.7, "HumidityMax": 92, "HumidityMin": 10, "stationId": "sm20", "name": "Smoke RMK 115 (Smoke #20)", "WindAvg": 0.6, "BaroPress": "", "VoltageMax": 14.4, "date": "09/05/14", "ConcentrationMax": 150, "ConcentrationMin": 0, "VoltageMean": 14.2}, {"LastObv": "24:00", "latitude": 43.7486, "VoltageMean": 14, "longitude": -122.4677, "name": "Smoke RMK 117 (Smoke #22)", "HumidityMin": 3, "qcReportLink": "https://tools.airfire.org/monitor-qc-report/v2/wrcc?unitID=sm22", "VoltageMax": 14.4, "ConcentrationMean": 10344, "HumidityMean": 46, "WindDir": 136, "date": "09/05/14", "ConcentrationMin": 0, "HumidityMax": 85, "AirFlowMean": 3.74, "stationId": "sm22", "VoltageMin": 9, "TempMin": -122.4, "TempMax": 42, "ConcentrationMax": 248000, "stationChartLink": "https://wrcc.dri.edu/cgi-bin/rawMAIN4.pl?idsm22+05+09+14+M", "BaroPress": 935.6, "TempMean": 17.4, "WindAvg": 0.9}, {"name": "Smoke USFS R1-53", "HumidityMax": 99, "latitude": 47.5354, "date": "09/05/14", "ConcentrationMax": 13, "ConcentrationMin": 0, "VoltageMax": 14.4, "stationChartLink": "https://wrcc.dri.edu/cgi-bin/rawMAIN4.pl?ids153+05+09+14+M", "qcReportLink": "https://tools.airfire.org/monitor-qc-report/v4/wrcc?unitID=s153", "longitude": -113.721, "HumidityMin": 26, "WindDir": "", "BaroPress": 894.5, "VoltageMin": 14.1, "AirFlowMean": 2, "LastObv": "23:00", "ConcentrationMean": 3, "VoltageMean": 14.3, "stationId": "s153", "WindAvg": 0.8, "HumidityMean": 64, "TempMean": 12.5, "TempMin": 3.2, "TempMax": 23.1}, {"VoltageMin": 14.2, "VoltageMean": 14.3, "qcReportLink": "https://tools.airfire.org/monitor-qc-report/v4/wrcc?unitID=s139", "HumidityMax": 76, "ConcentrationMax": 0, "WindAvg": 0.9, "LastObv": "24:00", "latitude": 46.9269, "ConcentrationMin": 0, "ConcentrationMean": 0, "TempMean": 16.8, "stationChartLink": "https://wrcc.dri.edu/cgi-bin/rawMAIN4.pl?ids139+05+09+14+M", "TempMax": 32.9, "HumidityMin": 8, "name": "Smoke USFS R1-39", "WindDir": 228, "AirFlowMean": 0, "HumidityMean": 48, "VoltageMax": 14.4, "TempMin": 6.4, "date": "09/05/14", "BaroPress": 909.8, "longitude": -114.0962, "stationId": "s139"}, {"longitude": -108.1473, "VoltageMax": 14, "HumidityMean": 1, "stationChartLink": "https://wrcc.dri.edu/cgi-bin/rawMAIN4.pl?ids278+05+09+14+M", "TempMin": 26.5, "stationId": "s278", "WindAvg": 0.3, "HumidityMin": "", "VoltageMean": 14, "ConcentrationMean": 0, "TempMean": 32.3, "TempMax": 35.8, "ConcentrationMax": 0, "BaroPress": 848.1, "latitude": 38.6935, "date": "09/05/14", "AirFlowMean": 1.98, "HumidityMax": "", "qcReportLink": "https://tools.airfire.org/monitor-qc-report/v4/wrcc?unitID=s278", "ConcentrationMin": 0, "LastObv": "24:00", "name": "Smoke USFS R2-78", "VoltageMin": 14, "WindDir": ""}, {"latitude": 35.8034, "name": "Smoke USFS R3-28", "VoltageMax": 14.2, "ConcentrationMin": -2, "LastObv": "24:00", "ConcentrationMax": 87, "VoltageMean": 14.2, "AirFlowMean": 16.67, "qcReportLink": "https://tools.airfire.org/monitor-qc-report/v4/wrcc?unitID=s328", "TempMean": 13.6, "date": "09/05/14", "WindAvg": 0.6, "VoltageMin": 14.1, "HumidityMean": 0, "TempMax": 20.1, "TempMin": 7.2, "longitude": -106.5888, "HumidityMax": 1, "WindDir": "", "BaroPress": -10, "stationId": "s328", "ConcentrationMean": 15, "HumidityMin": 0, "stationChartLink": "https://wrcc.dri.edu/cgi-bin/rawMAIN4.pl?ids328+05+09+14+M"}, {"qcReportLink": "https://tools.airfire.org/monitor-qc-report/v4/wrcc?unitID=s386", "ConcentrationMax": 5, "LastObv": "14:00", "HumidityMean": 0, "longitude": -105.9557, "TempMin": 14.8, "ConcentrationMean": 1, "WindDir": "", "VoltageMean": 14.3, "latitude": 35.6715, "stationChartLink": "https://wrcc.dri.edu/cgi-bin/rawMAIN4.pl?ids386+05+09+14+M", "ConcentrationMin": -5, "HumidityMin": "", "name": "Smoke USFS R3-86", "WindAvg": 1.7, "VoltageMax": 14.3, "TempMax": 22, "stationId": "s386", "VoltageMin": 14.3, "AirFlowMean": 16.69, "date": "09/05/14", "HumidityMax": "", "TempMean": 16.4, "BaroPress": -10}]}