{"response": [{"TempMax": 7.5, "latitude": 46.8432, "LastObv": "21:00", "HumidityMax": 70, "HumidityMean": 65, "VoltageMin": 14.4, "WindAvg": 0.9, "WindDir": "", "VoltageMean": 14.4, "ConcentrationMean": 0, "TempMin": 5.6, "BaroPress": 963.1, "ConcentrationMax": 1, "TempMean": 6.5, "HumidityMin": 61, "longitude": -92.078, "ConcentrationMin": 0, "VoltageMax": 14.4, "AirFlowMean": 2, "qcReportLink": "https://tools.airfire.org/monitor-qc-report/v4/wrcc?unitID=s960", "date": "04/13/14", "name": "Smoke USFS R9-60", "stationId": "s960", "stationChartLink": "https://wrcc.dri.edu/cgi-bin/rawMAIN4.pl?ids960+13+04+14+M"}, {"longitude": -82.6394, "VoltageMean": 14.1, "VoltageMax": 14.2, "AirFlowMean": 2, "ConcentrationMax": 121, "name": "Smoke #86", "latitude": 37.1646, "LastObv": "24:00", "WindAvg": 1.3, "ConcentrationMean": 30, "date": "04/13/14", "WindDir": 37, "HumidityMean": 52, "stationId": "sm86", "stationChartLink": "https://wrcc.dri.edu/cgi-bin/rawMAIN4.pl?idsm86+13+04+14+M", "HumidityMin": 24, "ConcentrationMin": 0, "TempMean": 21.5, "qcReportLink": "https://tools.airfire.org/monitor-qc-report/v4/wrcc?unitID=sm86", "TempMax": 31.2, "BaroPress": 959.7, "TempMin": 13.6, "VoltageMin": 13.9, "HumidityMax": 84}, {"ConcentrationMean": 15, "HumidityMin": 20, "name": "Smoke USFS R1-52", "VoltageMin": 14.1, "AirFlowMean": 2, "HumidityMax": 81, "HumidityMean": 52, "WindAvg": 0.9, "VoltageMax": 14.4, "longitude": -115.0584, "stationChartLink": "https://wrcc.dri.edu/cgi-bin/rawMAIN4.pl?ids152+13+04+14+M", "TempMax": 17.3, "stationId": "s152", "WindDir": 8, "qcReportLink": "https://tools.airfire.org/monitor-qc-report/v4/wrcc?unitID=s152", "latitude": 48.8978, "LastObv": "24:00", "ConcentrationMax": 94, "date": "04/13/14", "TempMin": -6, "TempMean": 4, "BaroPress": 930.8, "ConcentrationMin": 1, "VoltageMean": 14.3}, {"ConcentrationMin": 0, "TempMin": -2.6, "HumidityMax": 1, "WindDir": 1, "TempMax": 14, "stationChartLink": "https://wrcc.dri.edu/cgi-bin/rawMAIN4.pl?ids269+13+04+14+M", "WindAvg": 0.3, "VoltageMean": 14.4, "LastObv": "24:00", "TempMean": 4.4, "HumidityMin": 0, "BaroPress": 749, "longitude": -105.3637, "name": "Smoke USFS R2-69", "latitude": 38.9671, "date": "04/13/14", "VoltageMin": 14.3, "HumidityMean": 0, "ConcentrationMean": 1, "AirFlowMean": 2, "VoltageMax": 14.4, "ConcentrationMax": 2, "qcReportLink": "https://tools.airfire.org/monitor-qc-report/v4/wrcc?unitID=s269", "stationId": "s269"}]}