{"response": [{"VoltageMean": 14.5, "date": "01/26/23", "TempMean": 5.7, "WindAvg": 0.7, "VoltageMin": 14.4, "stationId": "s662", "TempMin": 3.5, "longitude": -114.0951, "name": "Smoke RMK 103 (Smoke #662)", "WindDir": "", "HumidityMean": 61, "qcReportLink": "https://tools.airfire.org/monitor-qc-report/v2/wrcc?unitID=s662", "VoltageMax": 14.5, "BaroPress": 914.1, "HumidityMin": 49, "TempMax": 9.2, "LastObv": "24:00", "ConcentrationMean": 3, "AirFlowMean": 1.97, "ConcentrationMax": 5, "ConcentrationMin": 1, "HumidityMax": 68, "latitude": 46.9275, "stationChartLink": "https://wrcc.dri.edu/cgi-bin/rawMAIN4.pl?ids662+26+01+23+M"}, {"AirFlowMean": 2, "HumidityMean": 34, "TempMax": 6.5, "ConcentrationMax": 0, "TempMin": -4.6, "date": "01/26/23", "TempMean": -0.7, "name": "Smoke RMK 129 (USFS R2-922)", "HumidityMax": 62, "VoltageMean": 14.4, "VoltageMin": 14.4, "qcReportLink": "https://tools.airfire.org/monitor-qc-report/v2/wrcc?unitID=2922", "BaroPress": 830.4, "stationId": "2922", "LastObv": "24:00", "WindDir": 175, "VoltageMax": 14.4, "stationChartLink": "https://wrcc.dri.edu/cgi-bin/rawMAIN4.pl?id2922+26+01+23+M", "latitude": 39.7144, "WindAvg": 2.2, "longitude": -105.124, "HumidityMin": 23, "ConcentrationMin": 0, "ConcentrationMean": 0}]}