{"response": [{"longitude": -106.2806, "BaroPress": 758.6, "stationChartLink": "https://wrcc.dri.edu/cgi-bin/rawMAIN4.pl?idsm17+23+07+16+M", "VoltageMax": 14.4, "LastObv": "24:00", "HumidityMean": 45, "latitude": 40.7326, "TempMax": 32.1, "WindAvg": 1.8, "stationId": "sm17", "TempMean": 20.5, "name": "Smoke RMK 105 (Smoke #17)", "VoltageMin": 14.1, "WindDir": 191, "AirFlowMean": 2, "qcReportLink": "https://tools.airfire.org/monitor-qc-report/v2/wrcc?unitID=sm17", "HumidityMax": 82, "HumidityMin": 22, "date": "07/23/16", "ConcentrationMin": 0, "TempMin": 8.7, "ConcentrationMax": 1, "ConcentrationMean": 0, "VoltageMean": 14.3}, {"stationChartLink": "https://wrcc.dri.edu/cgi-bin/rawMAIN4.pl?idsm23+23+07+16+M", "longitude": -105.6306, "ConcentrationMin": 0, "BaroPress": 785.5, "VoltageMin": 13.9, "TempMin": 16.1, "stationId": "sm23", "qcReportLink": "https://tools.airfire.org/monitor-qc-report/v2/wrcc?unitID=sm23", "HumidityMin": 18, "ConcentrationMax": 6, "ConcentrationMean": 3, "HumidityMax": 65, "HumidityMean": 39, "name": "Smoke RMK 118 (Smoke #23)", "date": "07/23/16", "TempMax": 33.9, "latitude": 41.3077, "AirFlowMean": 2, "LastObv": "24:00", "WindDir": 199, "VoltageMean": 14, "TempMean": 25.4, "VoltageMax": 14.2, "WindAvg": 1.5}, {"latitude": 38.4452, "WindAvg": 1, "VoltageMean": 14.1, "ConcentrationMax": 55, "VoltageMin": 14, "VoltageMax": 14.2, "WindDir": 85, "TempMax": 43.4, "LastObv": "24:00", "longitude": -105.1969, "stationChartLink": "https://wrcc.dri.edu/cgi-bin/rawMAIN4.pl?id2922+23+07+16+M", "BaroPress": 838.7, "qcReportLink": "https://tools.airfire.org/monitor-qc-report/v2/wrcc?unitID=2922", "HumidityMin": 12, "HumidityMean": 29, "ConcentrationMean": 14, "TempMean": 31.6, "TempMin": 22.2, "name": "Smoke RMK 129 (USFS R2-922)", "HumidityMax": 55, "stationId": "2922", "AirFlowMean": 2, "date": "07/23/16", "ConcentrationMin": 8}, {"longitude": -105.6876, "BaroPress": 807.5, "HumidityMean": 31, "ConcentrationMin": 0, "latitude": 38.3735, "date": "07/23/16", "VoltageMax": 14.3, "VoltageMean": 14.2, "WindDir": 249, "qcReportLink": "https://tools.airfire.org/monitor-qc-report/v2/wrcc?unitID=2924", "stationChartLink": "https://wrcc.dri.edu/cgi-bin/rawMAIN4.pl?id2924+23+07+16+M", "stationId": "2924", "TempMin": 18.9, "LastObv": "24:00", "ConcentrationMax": 91, "AirFlowMean": 2, "ConcentrationMean": 52, "name": "Smoke RMK 131 (USFS R2-924)", "VoltageMin": 14.1, "HumidityMin": 14, "TempMax": 37.7, "WindAvg": 1.8, "HumidityMax": 52, "TempMean": 28.1}, {"HumidityMax": 85, "stationId": "s152", "AirFlowMean": 2, "WindDir": 151, "WindAvg": 1.3, "HumidityMean": 54, "LastObv": "24:00", "VoltageMin": 14, "HumidityMin": 27, "stationChartLink": "https://wrcc.dri.edu/cgi-bin/rawMAIN4.pl?ids152+23+07+16+M", "date": "07/23/16", "longitude": -115.0584, "BaroPress": 925.3, "VoltageMean": 14.1, "VoltageMax": 14.2, "ConcentrationMean": 6, "TempMean": 20.7, "latitude": 48.8978, "TempMax": 29.5, "TempMin": 12.5, "ConcentrationMax": 10, "ConcentrationMin": 1, "qcReportLink": "https://tools.airfire.org/monitor-qc-report/v4/wrcc?unitID=s152", "name": "Smoke USFS R1-52"}, {"TempMin": 8.8, "HumidityMin": 0, "TempMean": 20.8, "date": "07/23/16", "latitude": 38.9792, "WindDir": 1, "HumidityMax": 1, "VoltageMean": 14.2, "ConcentrationMean": 1, "ConcentrationMax": 6, "ConcentrationMin": 0, "HumidityMean": 1, "WindAvg": 0.3, "LastObv": "24:00", "VoltageMax": 14.4, "BaroPress": 761.6, "TempMax": 34.9, "VoltageMin": 14, "stationId": "s269", "qcReportLink": "https://tools.airfire.org/monitor-qc-report/v4/wrcc?unitID=s269", "AirFlowMean": 2, "longitude": -105.353, "name": "Smoke USFS R2-69", "stationChartLink": "https://wrcc.dri.edu/cgi-bin/rawMAIN4.pl?ids269+23+07+16+M"}, {"TempMin": 1.3, "LastObv": "24:00", "HumidityMean": 39, "qcReportLink": "https://tools.airfire.org/monitor-qc-report/v4/wrcc?unitID=smy1", "HumidityMin": 6, "ConcentrationMax": 85, "VoltageMean": 14.4, "TempMax": 27.3, "longitude": -119.3555, "WindDir": 312, "WindAvg": 0.7, "latitude": 37.8751, "stationChartLink": "https://wrcc.dri.edu/cgi-bin/rawMAIN4.pl?idsmy1+23+07+16+M", "HumidityMax": 64, "BaroPress": -10, "stationId": "smy1", "TempMean": 13.2, "name": "Smoke NPS Yosemite 01", "ConcentrationMin": -3, "date": "07/23/16", "VoltageMax": 14.4, "ConcentrationMean": 15, "VoltageMin": 14.4, "AirFlowMean": 16.68}]}