{"response": [{"ConcentrationMin": 0, "name": "Smoke RMK 105 (Smoke #17)", "LastObv": "24:00", "HumidityMin": 8, "VoltageMax": 14.4, "TempMin": 14.5, "HumidityMax": 46, "TempMax": 42.2, "BaroPress": 888.4, "stationId": "sm17", "VoltageMean": 14.2, "WindDir": 120, "ConcentrationMean": 4, "VoltageMin": 14, "ConcentrationMax": 6, "HumidityMean": 21, "qcReportLink": "https://tools.airfire.org/monitor-qc-report/v2/wrcc?unitID=sm17", "TempMean": 29.1, "longitude": -110.7706, "WindAvg": 0.7, "stationChartLink": "https://wrcc.dri.edu/cgi-bin/rawMAIN4.pl?idsm17+09+06+17+M", "date": "06/09/17", "latitude": 33.378, "AirFlowMean": 2}, {"VoltageMin": 14, "HumidityMin": 8, "latitude": 39.7143, "ConcentrationMean": 2, "TempMax": 38.9, "longitude": -105.1239, "name": "Smoke RMK 116 (Smoke #21)", "ConcentrationMin": 2, "WindAvg": 1.6, "date": "06/09/17", "TempMean": 38.4, "TempMin": 38.1, "BaroPress": "", "stationChartLink": "https://wrcc.dri.edu/cgi-bin/rawMAIN4.pl?idsm21+09+06+17+M", "HumidityMean": 10, "qcReportLink": "https://tools.airfire.org/monitor-qc-report/v2/wrcc?unitID=sm21", "VoltageMean": 14, "LastObv": "24:00", "AirFlowMean": 2, "HumidityMax": 12, "ConcentrationMax": 2, "WindDir": "", "VoltageMax": 14, "stationId": "sm21"}, {"VoltageMean": 14.2, "VoltageMin": 14.1, "HumidityMean": 48, "date": "06/09/17", "stationId": "s153", "BaroPress": 915.4, "WindAvg": 1.7, "longitude": -115.0584, "latitude": 48.8978, "ConcentrationMean": 1, "TempMax": 25, "TempMin": 14.5, "stationChartLink": "https://wrcc.dri.edu/cgi-bin/rawMAIN4.pl?ids153+09+06+17+M", "qcReportLink": "https://tools.airfire.org/monitor-qc-report/v4/wrcc?unitID=s153", "WindDir": 24, "LastObv": "24:00", "AirFlowMean": 2, "ConcentrationMax": 2, "HumidityMax": 72, "ConcentrationMin": 1, "TempMean": 18.9, "name": "Smoke USFS R1-53", "VoltageMax": 14.3, "HumidityMin": 25}, {"latitude": 39.7144, "VoltageMean": 14.2, "TempMean": 26.7, "TempMax": 39.8, "TempMin": 15.6, "ConcentrationMin": 0, "VoltageMin": 14, "ConcentrationMean": 2, "AirFlowMean": 2, "name": "Smoke USFS R2-65", "BaroPress": 822, "stationChartLink": "https://wrcc.dri.edu/cgi-bin/rawMAIN4.pl?ids265+09+06+17+M", "stationId": "s265", "VoltageMax": 14.3, "HumidityMean": 31, "WindDir": 322, "qcReportLink": "https://tools.airfire.org/monitor-qc-report/v4/wrcc?unitID=s265", "LastObv": "24:00", "HumidityMin": 8, "ConcentrationMax": 6, "date": "06/09/17", "longitude": -105.1239, "HumidityMax": 62, "WindAvg": 1.1}, {"VoltageMax": 14.4, "stationId": "s269", "BaroPress": 756.5, "TempMean": 15.2, "HumidityMin": 0, "TempMax": 31.3, "LastObv": "19:00", "name": "Smoke USFS R2-69", "latitude": 38.9792, "WindAvg": 0.3, "qcReportLink": "https://tools.airfire.org/monitor-qc-report/v4/wrcc?unitID=s269", "stationChartLink": "https://wrcc.dri.edu/cgi-bin/rawMAIN4.pl?ids269+09+06+17+M", "VoltageMean": 14.3, "VoltageMin": 14, "HumidityMax": 1, "ConcentrationMax": 7, "longitude": -105.353, "date": "06/09/17", "HumidityMean": 1, "AirFlowMean": 2, "TempMin": 6.4, "WindDir": "", "ConcentrationMean": 3, "ConcentrationMin": 2}, {"date": "06/09/17", "ConcentrationMax": 18, "name": "Smoke USFS R3-86", "stationId": "s386", "stationChartLink": "https://wrcc.dri.edu/cgi-bin/rawMAIN4.pl?ids386+09+06+17+M", "latitude": 35.687, "LastObv": "24:00", "TempMean": 21.6, "VoltageMax": 14.1, "longitude": -105.8956, "VoltageMin": 13.8, "HumidityMin": "", "HumidityMean": 0, "VoltageMean": 14, "WindAvg": 0.4, "TempMin": 10.3, "TempMax": 33.2, "qcReportLink": "https://tools.airfire.org/monitor-qc-report/v4/wrcc?unitID=s386", "WindDir": 306, "AirFlowMean": 16.69, "ConcentrationMean": 4, "BaroPress": "", "ConcentrationMin": -5, "HumidityMax": ""}, {"HumidityMin": 30, "name": "Smoke NPS Yosemite 01", "TempMin": 12.7, "ConcentrationMin": -5, "AirFlowMean": 16.69, "WindDir": "", "TempMax": 21.8, "stationId": "smy1", "WindAvg": 0.4, "latitude": 37.6744, "stationChartLink": "https://wrcc.dri.edu/cgi-bin/rawMAIN4.pl?idsmy1+09+06+17+M", "VoltageMax": 14.4, "longitude": -119.784, "ConcentrationMax": 13, "HumidityMax": 90, "VoltageMin": 14.4, "ConcentrationMean": 4, "date": "06/09/17", "LastObv": "16:00", "TempMean": 15.5, "HumidityMean": 71, "qcReportLink": "https://tools.airfire.org/monitor-qc-report/v4/wrcc?unitID=smy1", "BaroPress": "", "VoltageMean": 14.4}]}