{"response": [{"TempMin": -1.6, "TempMean": 0.6, "latitude": 39.7144, "ConcentrationMean": 2, "stationId": "sm15", "name": "Smoke RMK 104 (Smoke #15)", "longitude": -105.124, "HumidityMean": 72, "LastObv": "24:00", "ConcentrationMax": 12, "date": "01/10/21", "BaroPress": 830.4, "AirFlowMean": 2, "stationChartLink": "https://wrcc.dri.edu/cgi-bin/rawMAIN4.pl?idsm15+10+01+21+M", "TempMax": 6.2, "WindAvg": 1.2, "HumidityMax": 84, "VoltageMean": 14.4, "WindDir": 180, "VoltageMin": 14.4, "ConcentrationMin": 0, "qcReportLink": "https://tools.airfire.org/monitor-qc-report/v2/wrcc?unitID=sm15", "VoltageMax": 14.4, "HumidityMin": 48}, {"HumidityMax": 94, "stationId": "sm67", "qcReportLink": "https://tools.airfire.org/monitor-qc-report/v2/wrcc?unitID=sm67", "HumidityMean": 82, "WindDir": 180, "TempMean": -0.2, "VoltageMean": 14.4, "ConcentrationMean": 7, "BaroPress": 831.5, "WindAvg": 1.1, "VoltageMin": 14.4, "TempMax": 4.6, "HumidityMin": 59, "longitude": -105.1239, "latitude": 39.7143, "ConcentrationMax": 13, "ConcentrationMin": 3, "VoltageMax": 14.4, "AirFlowMean": 2, "stationChartLink": "https://wrcc.dri.edu/cgi-bin/rawMAIN4.pl?idsm67+10+01+21+M", "LastObv": "24:00", "date": "01/10/21", "TempMin": -2, "name": "Smoke RMK 107 (Smoke #67)"}, {"date": "01/10/21", "AirFlowMean": 2, "WindDir": 178, "WindAvg": 1.2, "ConcentrationMean": 6, "BaroPress": 832.4, "longitude": -105.1239, "VoltageMean": 14.4, "VoltageMin": 14.4, "stationId": "s209", "qcReportLink": "https://tools.airfire.org/monitor-qc-report/v2/wrcc?unitID=s209", "ConcentrationMin": 3, "stationChartLink": "https://wrcc.dri.edu/cgi-bin/rawMAIN4.pl?ids209+10+01+21+M", "VoltageMax": 14.4, "TempMean": -0.9, "TempMax": 4.3, "HumidityMean": 80, "TempMin": -2.8, "HumidityMin": 53, "HumidityMax": 92, "ConcentrationMax": 14, "LastObv": "24:00", "name": "Smoke RMK 123 (Smoke #209)", "latitude": 39.7144}, {"qcReportLink": "https://tools.airfire.org/monitor-qc-report/v2/wrcc?unitID=s210", "ConcentrationMean": 6, "longitude": -106.0068, "TempMean": -11, "date": "01/10/21", "HumidityMax": 78, "WindDir": 178, "LastObv": "24:00", "ConcentrationMin": 1, "WindAvg": 0.8, "VoltageMean": 14.4, "latitude": 39.5948, "TempMax": 1.2, "VoltageMin": 14.4, "BaroPress": 726.1, "AirFlowMean": 2, "ConcentrationMax": 22, "HumidityMin": 33, "TempMin": -23.3, "HumidityMean": 63, "stationChartLink": "https://wrcc.dri.edu/cgi-bin/rawMAIN4.pl?ids210+10+01+21+M", "name": "Smoke RMK 124 (Smoke #210)", "VoltageMax": 14.4, "stationId": "s210"}, {"WindAvg": 0.8, "VoltageMean": 14.4, "qcReportLink": "https://tools.airfire.org/monitor-qc-report/v2/wrcc?unitID=2922", "longitude": -105.1239, "LastObv": "24:00", "ConcentrationMax": 14, "HumidityMean": 80, "latitude": 39.7144, "TempMean": 1.1, "name": "Smoke RMK 129 (USFS R2-922)", "TempMin": -1.2, "TempMax": 7.9, "HumidityMax": 93, "VoltageMax": 14.4, "WindDir": 175, "BaroPress": 830, "AirFlowMean": 2, "stationId": "2922", "HumidityMin": 53, "ConcentrationMean": 5, "ConcentrationMin": 2, "VoltageMin": 14.4, "date": "01/10/21", "stationChartLink": "https://wrcc.dri.edu/cgi-bin/rawMAIN4.pl?id2922+10+01+21+M"}, {"LastObv": "24:00", "date": "01/10/21", "AirFlowMean": 0, "HumidityMax": "", "ConcentrationMin": 0, "qcReportLink": "https://tools.airfire.org/monitor-qc-report/v4/wrcc?unitID=s328", "stationId": "s328", "VoltageMin": 14.4, "TempMin": -6.2, "TempMean": -3.1, "WindAvg": 1.2, "HumidityMin": "", "ConcentrationMax": 0, "latitude": 35.6715, "name": "Smoke USFS R3-28", "ConcentrationMean": 0, "TempMax": 0.5, "BaroPress": "", "VoltageMean": 14.4, "HumidityMean": 0, "longitude": -105.9557, "VoltageMax": 14.4, "WindDir": 256, "stationChartLink": "https://wrcc.dri.edu/cgi-bin/rawMAIN4.pl?ids328+10+01+21+M"}, {"WindDir": 178, "HumidityMin": 32, "VoltageMin": 14.4, "VoltageMax": 14.4, "qcReportLink": "https://tools.airfire.org/monitor-qc-report/v4/wrcc?unitID=2264", "TempMin": -13.3, "LastObv": "24:00", "date": "01/10/21", "stationChartLink": "https://wrcc.dri.edu/cgi-bin/rawMAIN4.pl?id2264+10+01+21+M", "AirFlowMean": 2, "longitude": -105.5637, "ConcentrationMax": 5, "stationId": "2264", "HumidityMean": 73, "latitude": 40.3613, "VoltageMean": 14.4, "TempMean": -4.1, "TempMax": 4.7, "WindAvg": 0.7, "HumidityMax": 88, "name": "Smoke USFS R2-264", "ConcentrationMin": 0, "BaroPress": 764.3, "ConcentrationMean": 1}]}