{"response": [{"TempMin": 3.5, "qcReportLink": "https://tools.airfire.org/monitor-qc-report/v2/wrcc?unitID=s659", "HumidityMax": 91, "VoltageMean": 14.3, "VoltageMin": 14.2, "latitude": 37.7822, "date": "11/21/23", "ConcentrationMin": 4, "stationId": "s659", "LastObv": "13:00", "BaroPress": 989, "ConcentrationMax": 11, "TempMean": 4.9, "HumidityMean": 75, "HumidityMin": 64, "stationChartLink": "https://wrcc.dri.edu/cgi-bin/rawMAIN4.pl?ids659+21+11+23+M", "AirFlowMean": 2, "VoltageMax": 14.4, "name": "Smoke RMK 100 (Smoke #659)", "ConcentrationMean": 6, "WindAvg": 0.7, "WindDir": "", "longitude": -79.4524, "TempMax": 6}, {"VoltageMean": 13.9, "ConcentrationMean": 1, "name": "Smoke USFS R3-86", "HumidityMax": 1, "qcReportLink": "https://tools.airfire.org/monitor-qc-report/v4/wrcc?unitID=s386", "ConcentrationMax": 7, "TempMin": -11.3, "stationChartLink": "https://wrcc.dri.edu/cgi-bin/rawMAIN4.pl?ids386+21+11+23+M", "date": "11/21/23", "HumidityMean": 1, "BaroPress": "", "VoltageMax": 14, "HumidityMin": 0, "TempMax": 0.5, "longitude": -105.8956, "TempMean": -6.6, "VoltageMin": 13.9, "stationId": "s386", "ConcentrationMin": -5, "LastObv": "24:00", "WindAvg": 0.4, "latitude": 35.687, "WindDir": 353, "AirFlowMean": 16.7}, {"TempMean": 1.8, "name": "Smoke USFS R1-307", "ConcentrationMean": 1, "ConcentrationMin": 0, "TempMax": 9.6, "VoltageMax": 14.4, "WindAvg": 0.9, "WindDir": 338, "VoltageMin": 14.3, "HumidityMax": 71, "date": "11/21/23", "HumidityMin": 40, "latitude": 46.5842, "longitude": -112.0418, "AirFlowMean": 2, "TempMin": -2.6, "stationChartLink": "https://wrcc.dri.edu/cgi-bin/rawMAIN4.pl?id1307+21+11+23+M", "qcReportLink": "https://tools.airfire.org/monitor-qc-report/v4/wrcc?unitID=1307", "HumidityMean": 58, "ConcentrationMax": 4, "LastObv": "24:00", "stationId": "1307", "BaroPress": "", "VoltageMean": 14.4}, {"AirFlowMean": 0, "VoltageMax": 14.1, "ConcentrationMean": 0, "VoltageMean": 14.1, "date": "11/21/23", "latitude": 46.9272, "TempMean": 18.9, "WindDir": "", "ConcentrationMin": 0, "ConcentrationMax": 0, "name": "Smoke USFS 3016", "TempMin": 18.3, "longitude": -114.0958, "stationId": "s316", "WindAvg": 0.3, "stationChartLink": "https://wrcc.dri.edu/cgi-bin/rawMAIN4.pl?ids316+21+11+23+M", "HumidityMin": "", "qcReportLink": "https://tools.airfire.org/monitor-qc-report/v4/wrcc?unitID=s316", "BaroPress": 920.5, "HumidityMax": "", "VoltageMin": 14.1, "HumidityMean": 40, "TempMax": 19.4, "LastObv": "24:00"}, {"WindDir": 243, "HumidityMean": 70, "ConcentrationMean": 4, "name": "Lolo NF Smoke #1", "TempMin": -1.4, "VoltageMin": 14.2, "AirFlowMean": 2, "LastObv": "24:00", "date": "11/21/23", "VoltageMean": 14.4, "longitude": -114.0962, "TempMean": 3, "stationId": "sml1", "VoltageMax": 14.4, "stationChartLink": "https://wrcc.dri.edu/cgi-bin/rawMAIN4.pl?idsml1+21+11+23+M", "latitude": 46.9269, "HumidityMax": 83, "BaroPress": 923.5, "HumidityMin": 49, "qcReportLink": "https://tools.airfire.org/monitor-qc-report/v4/wrcc?unitID=sml1", "ConcentrationMax": 14, "TempMax": 7.4, "WindAvg": 0.6, "ConcentrationMin": 1}, {"stationId": "sml2", "date": "11/21/23", "HumidityMin": 86, "VoltageMin": 14.3, "HumidityMax": 100, "ConcentrationMean": 2, "VoltageMax": 14.4, "BaroPress": 923.7, "AirFlowMean": 2, "ConcentrationMax": 12, "LastObv": "24:00", "VoltageMean": 14.4, "ConcentrationMin": 0, "name": "Lolo NF Smoke #2", "TempMax": 7.3, "stationChartLink": "https://wrcc.dri.edu/cgi-bin/rawMAIN4.pl?idsml2+21+11+23+M", "WindDir": 252, "longitude": -114.0962, "WindAvg": 0.6, "TempMin": -1.4, "qcReportLink": "https://tools.airfire.org/monitor-qc-report/v4/wrcc?unitID=sml2", "latitude": 46.9268, "HumidityMean": 98, "TempMean": 3}]}