{"response": [{"AirFlowMean": 2, "stationId": "sm13", "ConcentrationMean": 1, "LastObv": "24:00", "HumidityMean": 67, "VoltageMax": 14.3, "ConcentrationMin": 0, "TempMean": 13, "ConcentrationMax": 1, "BaroPress": 954.3, "TempMin": 7.7, "TempMax": 19.4, "WindDir": 115, "WindAvg": 1, "VoltageMin": 14.1, "stationChartLink": "https://wrcc.dri.edu/cgi-bin/rawMAIN4.pl?idsm13+17+09+11+M", "latitude": 45.522, "qcReportLink": "https://tools.airfire.org/monitor-qc-report/v4/wrcc?unitID=sm13", "HumidityMax": 83, "date": "09/17/11", "VoltageMean": 14.2, "longitude": -121.5939, "HumidityMin": 47, "name": "Smoke #13"}, {"ConcentrationMean": 4, "WindDir": 48, "stationId": "sm15", "HumidityMin": 37, "VoltageMin": 14, "VoltageMean": 14.2, "TempMax": 20.5, "AirFlowMean": 2, "WindAvg": 0.7, "ConcentrationMin": 3, "HumidityMean": 75, "latitude": 45.405, "ConcentrationMax": 5, "name": "Smoke RMK 104 (Smoke #15)", "stationChartLink": "https://wrcc.dri.edu/cgi-bin/rawMAIN4.pl?idsm15+17+09+11+M", "LastObv": "24:00", "TempMean": 11.2, "BaroPress": 986.7, "qcReportLink": "https://tools.airfire.org/monitor-qc-report/v2/wrcc?unitID=sm15", "HumidityMax": 89, "longitude": -122.2933, "date": "09/17/11", "TempMin": 6.5, "VoltageMax": 14.3}, {"HumidityMax": 91, "HumidityMin": 41, "ConcentrationMax": 14, "name": "Smoke RMK 113 (Smoke #16)", "BaroPress": "", "VoltageMax": 14.3, "ConcentrationMin": 5, "TempMean": 22, "stationChartLink": "https://wrcc.dri.edu/cgi-bin/rawMAIN4.pl?idsm16+17+09+11+M", "TempMax": 31.5, "longitude": -86.0801, "AirFlowMean": 2, "date": "09/17/11", "HumidityMean": 70, "LastObv": "24:00", "VoltageMin": 14, "qcReportLink": "https://tools.airfire.org/monitor-qc-report/v2/wrcc?unitID=sm16", "VoltageMean": 14.2, "ConcentrationMean": 9, "TempMin": 14.4, "latitude": 33.4413, "WindAvg": 0.8, "WindDir": 55, "stationId": "sm16"}, {"longitude": -85.6853, "LastObv": "24:00", "VoltageMean": 14.2, "latitude": 33.693, "BaroPress": "", "ConcentrationMax": 13, "qcReportLink": "https://tools.airfire.org/monitor-qc-report/v2/wrcc?unitID=sm21", "TempMax": 33.5, "WindDir": 355, "TempMean": 22.5, "VoltageMax": 14.3, "AirFlowMean": 2, "HumidityMin": 41, "HumidityMean": 75, "date": "09/17/11", "stationChartLink": "https://wrcc.dri.edu/cgi-bin/rawMAIN4.pl?idsm21+17+09+11+M", "ConcentrationMin": 3, "VoltageMin": 14, "stationId": "sm21", "HumidityMax": 97, "TempMin": 14.1, "name": "Smoke RMK 116 (Smoke #21)", "WindAvg": 0.6, "ConcentrationMean": 8}]}