{"response": [{"stationChartLink": "https://wrcc.dri.edu/cgi-bin/rawMAIN4.pl?idsm13+09+07+15+M", "LastObv": "24:00", "HumidityMean": 69, "VoltageMax": 14.2, "AirFlowMean": 2, "VoltageMean": 14.1, "VoltageMin": 14, "name": "Smoke #13", "ConcentrationMin": 10, "ConcentrationMax": 83, "HumidityMax": 89, "BaroPress": 996.1, "TempMean": 8.1, "ConcentrationMean": 45, "HumidityMin": 50, "date": "07/09/15", "WindDir": 12, "longitude": -152.1159, "latitude": 65.1732, "TempMax": 12.6, "WindAvg": 0.7, "TempMin": 5, "qcReportLink": "https://tools.airfire.org/monitor-qc-report/v4/wrcc?unitID=sm13", "stationId": "sm13"}, {"stationChartLink": "https://wrcc.dri.edu/cgi-bin/rawMAIN4.pl?idsm15+09+07+15+M", "latitude": 66.5704, "VoltageMean": 14.2, "LastObv": "23:00", "HumidityMean": 76, "HumidityMax": 88, "TempMean": 13.5, "longitude": -145.2444, "VoltageMax": 14.2, "qcReportLink": "https://tools.airfire.org/monitor-qc-report/v2/wrcc?unitID=sm15", "TempMin": 10.9, "ConcentrationMin": 0, "WindAvg": 0.8, "BaroPress": 992, "AirFlowMean": 2, "VoltageMin": 14.1, "date": "07/09/15", "HumidityMin": 38, "ConcentrationMax": 0, "name": "Smoke RMK 104 (Smoke #15)", "ConcentrationMean": 0, "stationId": "sm15", "WindDir": "", "TempMax": 20.9}, {"VoltageMin": 14.2, "LastObv": "24:00", "TempMin": 11.2, "ConcentrationMean": 3, "latitude": 64.7424, "ConcentrationMin": 0, "name": "Smoke RMK 105 (Smoke #17)", "TempMax": 25.9, "WindAvg": 0.3, "HumidityMax": 91, "qcReportLink": "https://tools.airfire.org/monitor-qc-report/v2/wrcc?unitID=sm17", "WindDir": 2, "VoltageMax": 14.4, "HumidityMin": 40, "longitude": -156.9546, "HumidityMean": 65, "VoltageMean": 14.3, "TempMean": 18.7, "stationChartLink": "https://wrcc.dri.edu/cgi-bin/rawMAIN4.pl?idsm17+09+07+15+M", "ConcentrationMax": 15, "stationId": "sm17", "AirFlowMean": 2, "BaroPress": 999.5, "date": "07/09/15"}, {"BaroPress": "", "ConcentrationMax": 18, "HumidityMax": 91, "latitude": 47.4687, "date": "07/09/15", "longitude": -123.8472, "HumidityMean": 76, "ConcentrationMin": 1, "TempMin": 16.3, "TempMean": 21.4, "stationChartLink": "https://wrcc.dri.edu/cgi-bin/rawMAIN4.pl?idsm21+09+07+15+M", "VoltageMin": 14.1, "stationId": "sm21", "WindDir": 114, "VoltageMean": 14.2, "ConcentrationMean": 5, "TempMax": 30.7, "AirFlowMean": 2, "LastObv": "24:00", "qcReportLink": "https://tools.airfire.org/monitor-qc-report/v2/wrcc?unitID=sm21", "name": "Smoke RMK 116 (Smoke #21)", "VoltageMax": 14.3, "WindAvg": 0.7, "HumidityMin": 51}, {"LastObv": "24:00", "HumidityMax": 49, "ConcentrationMax": 24, "latitude": 46.9269, "HumidityMin": 6, "VoltageMax": 14.4, "BaroPress": 898.3, "VoltageMin": 14.1, "TempMin": 14.8, "AirFlowMean": 2, "name": "Smoke #25", "ConcentrationMin": 10, "qcReportLink": "https://tools.airfire.org/monitor-qc-report/v4/wrcc?unitID=sm25", "TempMean": 26.7, "TempMax": 41.5, "longitude": -114.0962, "HumidityMean": 27, "stationChartLink": "https://wrcc.dri.edu/cgi-bin/rawMAIN4.pl?idsm25+09+07+15+M", "stationId": "sm25", "date": "07/09/15", "VoltageMean": 14.2, "WindAvg": 1, "ConcentrationMean": 19, "WindDir": 283}, {"stationChartLink": "https://wrcc.dri.edu/cgi-bin/rawMAIN4.pl?idsmy1+09+07+15+M", "TempMean": 20, "HumidityMax": 88, "VoltageMin": 14.3, "qcReportLink": "https://tools.airfire.org/monitor-qc-report/v4/wrcc?unitID=smy1", "AirFlowMean": 16.69, "VoltageMean": 14.4, "HumidityMin": 24, "WindDir": 185, "ConcentrationMax": 22, "ConcentrationMean": 5, "HumidityMean": 52, "WindAvg": 0.6, "latitude": 37.6745, "TempMax": 28.3, "date": "07/09/15", "name": "Smoke NPS Yosemite 01", "BaroPress": -10, "LastObv": "24:00", "VoltageMax": 14.4, "TempMin": 13.8, "ConcentrationMin": -5, "stationId": "smy1", "longitude": -119.784}]}