{"response": [{"qcReportLink": "https://tools.airfire.org/monitor-qc-report/v2/wrcc?unitID=sm67", "VoltageMean": 12.4, "stationChartLink": "https://wrcc.dri.edu/cgi-bin/rawMAIN4.pl?idsm67+22+06+21+M", "HumidityMin": 5, "LastObv": "24:00", "VoltageMax": 13, "TempMax": 42, "ConcentrationMin": 0, "latitude": 35.0509, "date": "06/22/21", "BaroPress": 852.1, "HumidityMean": 16, "longitude": -110.6843, "TempMean": 29.7, "WindAvg": 1.3, "name": "Smoke RMK 107 (Smoke #67)", "VoltageMin": 11.9, "TempMin": 16.3, "WindDir": 256, "AirFlowMean": 2, "ConcentrationMax": 11, "stationId": "sm67", "ConcentrationMean": 2, "HumidityMax": 36}, {"ConcentrationMean": 1, "qcReportLink": "https://tools.airfire.org/monitor-qc-report/v2/wrcc?unitID=sm16", "WindAvg": 1, "longitude": -105.1239, "LastObv": "24:00", "VoltageMean": 14.1, "stationId": "sm16", "VoltageMax": 14.3, "ConcentrationMin": 0, "VoltageMin": 13.9, "TempMean": 22.2, "BaroPress": 824.5, "WindDir": 180, "TempMin": 12, "date": "06/22/21", "TempMax": 35.8, "latitude": 39.7144, "name": "Smoke RMK 113 (Smoke #16)", "ConcentrationMax": 9, "HumidityMean": 52, "AirFlowMean": 1.97, "stationChartLink": "https://wrcc.dri.edu/cgi-bin/rawMAIN4.pl?idsm16+22+06+21+M", "HumidityMax": 85, "HumidityMin": 17}, {"name": "Smoke RMK 114 (Smoke #19)", "HumidityMean": 13, "VoltageMax": 14.1, "longitude": -109.2268, "HumidityMin": 3, "VoltageMean": 13.9, "qcReportLink": "https://tools.airfire.org/monitor-qc-report/v2/wrcc?unitID=sm19", "WindDir": 129, "TempMean": 35.2, "AirFlowMean": 2, "WindAvg": 2, "date": "06/22/21", "stationChartLink": "https://wrcc.dri.edu/cgi-bin/rawMAIN4.pl?idsm19+22+06+21+M", "VoltageMin": 13.8, "ConcentrationMax": 19, "ConcentrationMean": 4, "latitude": 32.9476, "TempMax": 45.2, "TempMin": 23.4, "LastObv": "24:00", "HumidityMax": 27, "ConcentrationMin": 1, "BaroPress": "", "stationId": "sm19"}, {"qcReportLink": "https://tools.airfire.org/monitor-qc-report/v2/wrcc?unitID=sm21", "ConcentrationMax": 1, "HumidityMin": "", "AirFlowMean": 1.7, "HumidityMax": "", "VoltageMin": 14.1, "WindDir": "", "LastObv": "24:00", "TempMin": "", "longitude": -105.1239, "WindAvg": 1.2, "TempMean": 31.4, "HumidityMean": 18, "ConcentrationMin": 1, "name": "Smoke RMK 116 (Smoke #21)", "latitude": 39.7143, "TempMax": "", "stationId": "sm21", "BaroPress": "", "VoltageMean": 14.1, "date": "06/22/21", "ConcentrationMean": 1, "VoltageMax": 14.1, "stationChartLink": "https://wrcc.dri.edu/cgi-bin/rawMAIN4.pl?idsm21+22+06+21+M"}, {"VoltageMax": 14, "LastObv": "24:00", "ConcentrationMin": 0, "WindAvg": 2.2, "HumidityMin": 7, "BaroPress": 871.8, "VoltageMean": 14, "latitude": 33.0556, "HumidityMax": 26, "TempMin": 23.7, "stationChartLink": "https://wrcc.dri.edu/cgi-bin/rawMAIN4.pl?idsm23+22+06+21+M", "name": "Smoke RMK 118 (Smoke #23)", "ConcentrationMean": 9, "AirFlowMean": 2, "HumidityMean": 16, "ConcentrationMax": 37, "VoltageMin": 13.9, "longitude": -109.3282, "WindDir": 284, "TempMean": 31.5, "stationId": "sm23", "qcReportLink": "https://tools.airfire.org/monitor-qc-report/v2/wrcc?unitID=sm23", "date": "06/22/21", "TempMax": 39.5}, {"HumidityMin": 3, "VoltageMax": 14.2, "TempMin": 21.2, "ConcentrationMax": 51, "latitude": 33.2937, "TempMean": 33.3, "stationChartLink": "https://wrcc.dri.edu/cgi-bin/rawMAIN4.pl?ids217+22+06+21+M", "HumidityMax": 29, "name": "Smoke RMK 126 (Smoke #217)", "AirFlowMean": 2, "LastObv": "24:00", "WindDir": 359, "HumidityMean": 16, "BaroPress": 918.6, "VoltageMean": 14.1, "TempMax": 45.8, "ConcentrationMin": 2, "VoltageMin": 14, "WindAvg": 1.4, "ConcentrationMean": 8, "stationId": "s217", "qcReportLink": "https://tools.airfire.org/monitor-qc-report/v2/wrcc?unitID=s217", "longitude": -110.4455, "date": "06/22/21"}, {"LastObv": "24:00", "VoltageMax": 14.1, "VoltageMean": 14, "VoltageMin": 13.9, "date": "06/22/21", "WindDir": 203, "ConcentrationMax": 5, "HumidityMean": 23, "HumidityMin": 13, "qcReportLink": "https://tools.airfire.org/monitor-qc-report/v2/wrcc?unitID=s457", "ConcentrationMin": 3, "stationId": "s457", "TempMin": 26.9, "WindAvg": 1.7, "latitude": 33.294, "TempMax": 41.1, "TempMean": 34.8, "ConcentrationMean": 4, "stationChartLink": "https://wrcc.dri.edu/cgi-bin/rawMAIN4.pl?ids457+22+06+21+M", "HumidityMax": 31, "BaroPress": 932.7, "AirFlowMean": 2, "longitude": -111.2858, "name": "Smoke RMK 128 (Smoke #457)"}, {"TempMin": 19.7, "WindDir": 165, "ConcentrationMean": 6, "LastObv": "24:00", "AirFlowMean": 2, "latitude": 33.0694, "longitude": -110.0194, "stationChartLink": "https://wrcc.dri.edu/cgi-bin/rawMAIN4.pl?id2923+22+06+21+M", "qcReportLink": "https://tools.airfire.org/monitor-qc-report/v2/wrcc?unitID=2923", "ConcentrationMin": 2, "ConcentrationMax": 18, "VoltageMax": 14.2, "HumidityMean": 19, "VoltageMin": 13.9, "name": "Smoke RMK 130 (USFS R2-923)", "date": "06/22/21", "HumidityMin": 6, "WindAvg": 1.8, "HumidityMax": 34, "TempMax": 45.6, "TempMean": 33.5, "BaroPress": 914.5, "VoltageMean": 14, "stationId": "2923"}, {"HumidityMin": 2, "date": "06/22/21", "stationChartLink": "https://wrcc.dri.edu/cgi-bin/rawMAIN4.pl?ids265+22+06+21+M", "TempMin": 20.6, "TempMax": 42.9, "VoltageMean": 14.1, "VoltageMin": 14, "LastObv": "19:00", "TempMean": 30.3, "ConcentrationMean": 4, "WindDir": "", "ConcentrationMin": 0, "longitude": -110.7913, "HumidityMax": 30, "ConcentrationMax": 10, "name": "Smoke USFS R2-65", "latitude": 33.3973, "WindAvg": 0.3, "qcReportLink": "https://tools.airfire.org/monitor-qc-report/v4/wrcc?unitID=s265", "BaroPress": 892.4, "HumidityMean": 17, "AirFlowMean": 2, "stationId": "s265", "VoltageMax": 14.2}, {"TempMax": "", "VoltageMean": 14.1, "date": "06/22/21", "VoltageMax": 14.2, "HumidityMean": 100, "HumidityMax": "", "TempMin": "", "ConcentrationMean": 8, "qcReportLink": "https://tools.airfire.org/monitor-qc-report/v4/wrcc?unitID=s328", "stationChartLink": "https://wrcc.dri.edu/cgi-bin/rawMAIN4.pl?ids328+22+06+21+M", "AirFlowMean": 16.69, "LastObv": "24:00", "latitude": 35.6715, "longitude": -105.9556, "HumidityMin": "", "VoltageMin": 14, "BaroPress": "", "stationId": "s328", "WindAvg": 3, "ConcentrationMin": -5, "WindDir": 358, "name": "Smoke USFS R3-28", "ConcentrationMax": 39, "TempMean": 31.9}, {"HumidityMax": 13, "TempMean": 20.4, "ConcentrationMax": 48, "WindAvg": 1.3, "BaroPress": "", "TempMin": 8.3, "ConcentrationMean": 16, "stationChartLink": "https://wrcc.dri.edu/cgi-bin/rawMAIN4.pl?ide418+22+06+21+M", "qcReportLink": "https://tools.airfire.org/monitor-qc-report/v2/wrcc?unitID=e418", "LastObv": "24:00", "HumidityMean": 5, "ConcentrationMin": -5, "latitude": 35.5363, "name": "Smoke RMK 408 (EBAM #418)", "VoltageMax": 14, "WindDir": 271, "longitude": -108.7271, "date": "06/22/21", "VoltageMean": 13.9, "HumidityMin": 0, "VoltageMin": 13.7, "stationId": "e418", "TempMax": 29.4, "AirFlowMean": 16.4}, {"ConcentrationMean": 10, "LastObv": "24:00", "VoltageMax": 14.3, "TempMax": 38.7, "HumidityMax": 61, "ConcentrationMin": 1, "TempMean": 28.4, "TempMin": 14.5, "date": "06/22/21", "BaroPress": "", "VoltageMin": 14.2, "name": "Smoke RMK 412 (EBAM #840)", "HumidityMin": 2, "WindDir": 333, "WindAvg": 1.2, "qcReportLink": "https://tools.airfire.org/monitor-qc-report/v2/wrcc?unitID=e840", "latitude": 35.173, "ConcentrationMax": 23, "stationId": "e840", "longitude": -107.821, "VoltageMean": 14.2, "stationChartLink": "https://wrcc.dri.edu/cgi-bin/rawMAIN4.pl?ide840+22+06+21+M", "AirFlowMean": 16.7, "HumidityMean": 23}, {"name": "AQB Smoke EBAM T-2", "stationChartLink": "https://wrcc.dri.edu/cgi-bin/rawMAIN4.pl?ideat2+22+06+21+M", "latitude": 36.7576, "VoltageMin": 14.1, "LastObv": "24:00", "date": "06/22/21", "AirFlowMean": 16.7, "TempMin": 17.4, "WindAvg": 0.8, "ConcentrationMean": 13, "VoltageMean": 14.2, "HumidityMax": 1, "HumidityMin": 0, "ConcentrationMin": -5, "VoltageMax": 14.2, "BaroPress": "", "ConcentrationMax": 93, "TempMean": 28.6, "longitude": -108.1822, "TempMax": 37.4, "stationId": "eat2", "WindDir": 177, "HumidityMean": 1, "qcReportLink": "https://tools.airfire.org/monitor-qc-report/v4/wrcc?unitID=eat2"}]}