{"response": [{"BaroPress": 875.7, "LastObv": "22:00", "name": "Smoke #13", "date": "08/23/16", "VoltageMean": 14.2, "ConcentrationMin": 3, "latitude": 44.0786, "longitude": -115.4959, "TempMin": 2.8, "WindAvg": 0.8, "qcReportLink": "https://tools.airfire.org/monitor-qc-report/v4/wrcc?unitID=sm13", "TempMax": 29.3, "VoltageMin": 13.9, "AirFlowMean": 1.73, "HumidityMean": 44, "ConcentrationMean": 46, "stationId": "sm13", "VoltageMax": 14.4, "stationChartLink": "https://wrcc.dri.edu/cgi-bin/rawMAIN4.pl?idsm13+23+08+16+M", "WindDir": "", "ConcentrationMax": 255, "TempMean": 14.4, "HumidityMax": 82, "HumidityMin": 8}, {"VoltageMin": 14.2, "stationChartLink": "https://wrcc.dri.edu/cgi-bin/rawMAIN4.pl?idsm17+23+08+16+M", "WindAvg": 1.1, "HumidityMin": 21, "BaroPress": 756.1, "VoltageMean": 14.3, "latitude": 40.7325, "WindDir": 154, "TempMin": 2.3, "HumidityMax": 87, "date": "08/23/16", "longitude": -106.2807, "TempMean": 13.7, "LastObv": "24:00", "TempMax": 25.9, "ConcentrationMean": 1, "name": "Smoke RMK 105 (Smoke #17)", "ConcentrationMax": 2, "VoltageMax": 14.4, "qcReportLink": "https://tools.airfire.org/monitor-qc-report/v2/wrcc?unitID=sm17", "ConcentrationMin": 1, "stationId": "sm17", "AirFlowMean": 2, "HumidityMean": 56}, {"WindAvg": 1.6, "HumidityMax": 54, "HumidityMin": 11, "TempMax": 30.1, "TempMin": 6.2, "VoltageMax": 14.4, "latitude": 44.4393, "TempMean": 17.8, "qcReportLink": "https://tools.airfire.org/monitor-qc-report/v2/wrcc?unitID=s284", "longitude": -118.1908, "stationChartLink": "https://wrcc.dri.edu/cgi-bin/rawMAIN4.pl?ids284+23+08+16+M", "ConcentrationMin": 0, "stationId": "s284", "HumidityMean": 30, "AirFlowMean": 2, "BaroPress": 879.1, "name": "Smoke RMK 109 (Smoke #84)", "date": "08/23/16", "WindDir": "", "ConcentrationMax": 196, "ConcentrationMean": 43, "VoltageMean": 14.2, "VoltageMin": 14, "LastObv": "24:00"}, {"VoltageMax": 14, "ConcentrationMin": 3, "VoltageMin": 14, "AirFlowMean": 1.95, "date": "08/23/16", "ConcentrationMax": 3, "latitude": 39.7144, "HumidityMax": 26, "stationChartLink": "https://wrcc.dri.edu/cgi-bin/rawMAIN4.pl?ids215+23+08+16+M", "stationId": "s215", "TempMin": 26.8, "HumidityMean": 23, "LastObv": "24:00", "WindAvg": 0.3, "HumidityMin": 19, "TempMax": 27.9, "name": "Smoke RMK 110 (Smoke #215)", "BaroPress": 827.4, "VoltageMean": 14, "WindDir": "", "TempMean": 27.3, "qcReportLink": "https://tools.airfire.org/monitor-qc-report/v2/wrcc?unitID=s215", "ConcentrationMean": 3, "longitude": -105.1239}, {"BaroPress": 894.9, "qcReportLink": "https://tools.airfire.org/monitor-qc-report/v2/wrcc?unitID=sm11", "TempMean": 15.8, "ConcentrationMax": 5, "longitude": -118.7094, "stationId": "sm11", "HumidityMin": 9, "stationChartLink": "https://wrcc.dri.edu/cgi-bin/rawMAIN4.pl?idsm11+23+08+16+M", "VoltageMin": 13.9, "latitude": 44.4561, "AirFlowMean": 2, "WindAvg": 0.9, "VoltageMax": 14.4, "HumidityMean": 35, "TempMax": 31.8, "LastObv": "24:00", "TempMin": 2.2, "ConcentrationMean": 3, "date": "08/23/16", "name": "Smoke RMK 112 (Smoke #11)", "ConcentrationMin": 2, "VoltageMean": 14.1, "WindDir": 269, "HumidityMax": 64}, {"stationChartLink": "https://wrcc.dri.edu/cgi-bin/rawMAIN4.pl?idsm19+23+08+16+M", "longitude": -115.4959, "date": "08/23/16", "latitude": 44.0787, "HumidityMean": 11, "ConcentrationMean": 22, "TempMax": 26.4, "VoltageMax": 14.1, "HumidityMax": "", "VoltageMin": 14, "name": "Smoke RMK 114 (Smoke #19)", "TempMin": 25.4, "LastObv": "24:00", "WindAvg": 0.7, "stationId": "sm19", "HumidityMin": "", "WindDir": "", "AirFlowMean": 1.75, "BaroPress": "", "TempMean": 25.9, "qcReportLink": "https://tools.airfire.org/monitor-qc-report/v2/wrcc?unitID=sm19", "ConcentrationMax": 26, "VoltageMean": 14.1, "ConcentrationMin": 19}, {"WindAvg": 1.1, "TempMean": 18, "date": "08/23/16", "TempMin": 3.2, "TempMax": 32.5, "AirFlowMean": 2, "LastObv": "24:00", "stationId": "sm22", "HumidityMean": 40, "name": "Smoke RMK 117 (Smoke #22)", "longitude": -115.9593, "VoltageMin": 14, "ConcentrationMax": 316, "qcReportLink": "https://tools.airfire.org/monitor-qc-report/v2/wrcc?unitID=sm22", "HumidityMin": 11, "WindDir": "", "BaroPress": 907.6, "stationChartLink": "https://wrcc.dri.edu/cgi-bin/rawMAIN4.pl?idsm22+23+08+16+M", "ConcentrationMean": 28, "VoltageMean": 14.2, "latitude": 44.0902, "VoltageMax": 14.4, "HumidityMax": 77, "ConcentrationMin": 0}, {"HumidityMax": 15, "VoltageMax": 14, "TempMin": 23.9, "TempMean": 27.8, "VoltageMin": 13.9, "LastObv": "24:00", "ConcentrationMax": 46, "WindDir": "", "AirFlowMean": 1.98, "ConcentrationMean": 15, "date": "08/23/16", "BaroPress": 875.8, "VoltageMean": 13.9, "longitude": -115.905, "HumidityMin": 11, "HumidityMean": 13, "stationId": "sm23", "TempMax": 29.7, "ConcentrationMin": 4, "qcReportLink": "https://tools.airfire.org/monitor-qc-report/v2/wrcc?unitID=sm23", "stationChartLink": "https://wrcc.dri.edu/cgi-bin/rawMAIN4.pl?idsm23+23+08+16+M", "latitude": 43.8942, "WindAvg": 2.3, "name": "Smoke RMK 118 (Smoke #23)"}, {"ConcentrationMax": 68, "longitude": -112.5471, "AirFlowMean": 2, "VoltageMax": 14.4, "TempMean": 17.4, "qcReportLink": "https://tools.airfire.org/monitor-qc-report/v2/wrcc?unitID=sm68", "name": "Smoke RMK 121 (Smoke #68)", "ConcentrationMin": 0, "date": "08/23/16", "TempMax": 28.7, "latitude": 38.3394, "WindAvg": 0.7, "stationId": "sm68", "WindDir": 28, "HumidityMean": 72, "HumidityMin": 30, "VoltageMean": 14.3, "BaroPress": 798.5, "VoltageMin": 14.1, "TempMin": 10.9, "stationChartLink": "https://wrcc.dri.edu/cgi-bin/rawMAIN4.pl?idsm68+23+08+16+M", "LastObv": "24:00", "ConcentrationMean": 26, "HumidityMax": 100}, {"TempMin": -3.8, "HumidityMin": 7, "WindDir": 223, "BaroPress": 802.8, "date": "08/23/16", "VoltageMin": 14.2, "longitude": -114.9268, "ConcentrationMean": 51, "ConcentrationMax": 95, "ConcentrationMin": 16, "qcReportLink": "https://tools.airfire.org/monitor-qc-report/v2/wrcc?unitID=s217", "VoltageMean": 14.3, "HumidityMax": 64, "name": "Smoke RMK 126 (Smoke #217)", "VoltageMax": 14.4, "AirFlowMean": 2, "stationId": "s217", "TempMean": 11.3, "WindAvg": 1.4, "HumidityMean": 29, "latitude": 44.1708, "LastObv": "24:00", "TempMax": 26.3, "stationChartLink": "https://wrcc.dri.edu/cgi-bin/rawMAIN4.pl?ids217+23+08+16+M"}, {"AirFlowMean": 2, "WindAvg": 1.5, "VoltageMin": 14.1, "BaroPress": 805.8, "TempMax": 33.3, "HumidityMax": 85, "VoltageMax": 14.4, "WindDir": 266, "name": "Smoke RMK 131 (USFS R2-924)", "stationId": "2924", "date": "08/23/16", "TempMean": 20.3, "TempMin": 13.7, "longitude": -105.6876, "stationChartLink": "https://wrcc.dri.edu/cgi-bin/rawMAIN4.pl?id2924+23+08+16+M", "HumidityMean": 50, "ConcentrationMax": 4, "qcReportLink": "https://tools.airfire.org/monitor-qc-report/v2/wrcc?unitID=2924", "HumidityMin": 21, "ConcentrationMean": 1, "VoltageMean": 14.3, "ConcentrationMin": 0, "latitude": 38.3735, "LastObv": "24:00"}, {"WindDir": 304, "ConcentrationMax": 11, "name": "Smoke USFS R1-52", "HumidityMin": 23, "VoltageMax": 14.3, "qcReportLink": "https://tools.airfire.org/monitor-qc-report/v4/wrcc?unitID=s152", "TempMax": 24, "date": "08/23/16", "latitude": 48.8978, "ConcentrationMean": 6, "ConcentrationMin": 2, "stationChartLink": "https://wrcc.dri.edu/cgi-bin/rawMAIN4.pl?ids152+23+08+16+M", "AirFlowMean": 2, "WindAvg": 1.2, "stationId": "s152", "longitude": -115.0584, "TempMean": 17.5, "TempMin": 10.1, "BaroPress": 923.2, "HumidityMax": 68, "HumidityMean": 43, "VoltageMin": 14, "VoltageMean": 14.2, "LastObv": "24:00"}, {"date": "08/23/16", "TempMax": 29.6, "ConcentrationMax": 4, "VoltageMean": 14.3, "qcReportLink": "https://tools.airfire.org/monitor-qc-report/v4/wrcc?unitID=s269", "WindDir": 1, "BaroPress": 758.8, "AirFlowMean": 2, "LastObv": "24:00", "longitude": -105.3531, "TempMin": 4.5, "latitude": 38.9792, "VoltageMax": 14.4, "stationId": "s269", "HumidityMax": 1, "name": "Smoke USFS R2-69", "TempMean": 14.2, "stationChartLink": "https://wrcc.dri.edu/cgi-bin/rawMAIN4.pl?ids269+23+08+16+M", "ConcentrationMean": 2, "HumidityMin": 0, "HumidityMean": 1, "VoltageMin": 14, "WindAvg": 0.3, "ConcentrationMin": 1}, {"stationChartLink": "https://wrcc.dri.edu/cgi-bin/rawMAIN4.pl?idsmy1+23+08+16+M", "latitude": 37.6472, "VoltageMin": 14.4, "HumidityMin": 22, "ConcentrationMin": 2, "WindAvg": 0.8, "LastObv": "24:00", "TempMin": 11.3, "TempMax": 23, "AirFlowMean": 16.68, "longitude": -119.7039, "TempMean": 15.9, "VoltageMax": 14.4, "name": "Smoke NPS Yosemite 01", "HumidityMax": 53, "WindDir": 12, "date": "08/23/16", "ConcentrationMean": 10, "ConcentrationMax": 16, "stationId": "smy1", "VoltageMean": 14.4, "qcReportLink": "https://tools.airfire.org/monitor-qc-report/v4/wrcc?unitID=smy1", "HumidityMean": 39, "BaroPress": ""}, {"date": "08/23/16", "TempMax": 28.2, "VoltageMin": 14, "longitude": -114.0903, "HumidityMin": 24, "WindDir": "", "HumidityMax": 73, "HumidityMean": 46, "VoltageMean": 14.2, "TempMean": 16.6, "qcReportLink": "https://tools.airfire.org/monitor-qc-report/v4/wrcc?unitID=1306", "VoltageMax": 14.4, "TempMin": 7.4, "name": "Smoke USFS R1-306", "LastObv": "24:00", "stationChartLink": "https://wrcc.dri.edu/cgi-bin/rawMAIN4.pl?id1306+23+08+16+M", "AirFlowMean": 2, "ConcentrationMean": 4, "WindAvg": 1.3, "BaroPress": "", "ConcentrationMax": 18, "latitude": 46.7533, "ConcentrationMin": 0, "stationId": "1306"}]}